dalog/__init__.py
dalog/__main__.py
dalog/app.py
dalog/cli.py
dalog/config/__init__.py
dalog/config/defaults.py
dalog/config/loader.py
dalog/config/models.py
dalog/core/__init__.py
dalog/core/exclusions.py
dalog/core/file_watcher.py
dalog/core/html_processor.py
dalog/core/log_processor.py
dalog/core/log_reader.py
dalog/core/remote_reader.py
dalog/core/ssh_file_watcher.py
dalog/core/ssh_pool.py
dalog/core/styling.py
dalog/security/__init__.py
dalog/security/path_security.py
dalog/security/regex_security.py
dalog/utils/__init__.py
dalog/widgets/__init__.py
dalog/widgets/exclusion_modal.py
dalog/widgets/header.py
dalog/widgets/log_viewer.py
dalog-0.2.2.dist-info/licenses/LICENSE
dalog-0.2.2.dist-info/METADATA
dalog-0.2.2.dist-info/WHEEL
dalog-0.2.2.dist-info/entry_points.txt
dalog-0.2.2.dist-info/top_level.txt
dalog-0.2.2.dist-info/RECORD
