Metadata-Version: 2.4
Name: dalog
Version: 0.2.2
Summary: Your friendly terminal logs viewer
Author-email: Mike Wassmer <mikewassmer@protonmail.com>
License: MIT
Project-URL: Homepage, https://github.com/mwmdev/dalog
Project-URL: Repository, https://github.com/mwmdev/dalog.git
Project-URL: Issues, https://github.com/mwmdev/dalog/issues
Classifier: Development Status :: 3 - Alpha
Classifier: Environment :: Console
Classifier: Intended Audience :: Developers
Classifier: License :: OSI Approved :: MIT License
Classifier: Programming Language :: Python :: 3
Classifier: Programming Language :: Python :: 3.10
Classifier: Programming Language :: Python :: 3.11
Classifier: Programming Language :: Python :: 3.12
Classifier: Topic :: System :: Logging
Classifier: Topic :: Software Development :: Debuggers
Requires-Python: >=3.10
License-File: LICENSE
Requires-Dist: textual>=0.70.0
Requires-Dist: rich>=13.0.0
Requires-Dist: click>=8.0.0
Requires-Dist: pydantic>=2.0.0
Requires-Dist: watchdog>=3.0.0
Requires-Dist: pyyaml>=6.0
Requires-Dist: toml>=0.10.2
Requires-Dist: python-dateutil>=2.8.0
Requires-Dist: arrow>=1.2.0
Requires-Dist: beautifulsoup4>=4.12.0
Requires-Dist: html2text>=2020.1.16
Requires-Dist: regex>=2023.12.0
Requires-Dist: pyperclip>=1.8.0
Requires-Dist: paramiko>=3.0.0
Provides-Extra: dev
Requires-Dist: pytest>=7.0.0; extra == "dev"
Requires-Dist: pytest-asyncio>=0.21.0; extra == "dev"
Requires-Dist: pytest-cov>=4.0.0; extra == "dev"
Requires-Dist: black>=23.0.0; extra == "dev"
Requires-Dist: isort>=5.12.0; extra == "dev"
Requires-Dist: mypy>=1.0.0; extra == "dev"
Requires-Dist: pylint>=2.17.0; extra == "dev"
Dynamic: license-file
